{"peliculas": [{"director": "Karey Kirkpatrick, Jason Reisig", "sinopsis": "A Yeti is convinced that the elusive creatures known as hoomans really do exist", "genero": "Aventura", "cantidad": 5, "poster": "Smallfoot.jpg", "precio": 18, "anno": 2018, "actores": [{"nombre": "Jake Lloyd", "foto": "anakin.jpg", "personaje": "Anakin Skywalker"}, {"nombre": "Ewan McGregor", "foto": "kenobi.jpg", "personaje": "Obi-Wan Kenobi"}], "titulo": "Smallfoot", "fechaCompra": "2018-10-2", "id": 3, "valoracion": 5}, {"director": "Corin Hardy", "sinopsis": "Vente al lado oscuro Obi-Wan", "genero": "Terror", "cantidad": 8, "poster": "The_nun.jpg", "precio": 18, "anno": 199, "actores": [{"nombre": "Jake Lloyd", "foto": "anakin.jpg", "personaje": "Anakin Skywalker"}, {"nombre": "Ewan McGregor", "foto": "kenobi.jpg", "personaje": "Obi-Wan Kenobi"}], "titulo": "La monja", "fechaCompra": "201-10-27", "id": 2, "valoracion": 5}, {"anno": 2018, "sinopsis": "Documentary about ut rock star Joan Jett.", "genero": "Documental", "cantidad": 11, "poster": "Bad_reputation.jpg", "precio": 18.99, "director": "Kevin Kerslake", "actores": [{"nombre": "Billie Joe Armstrong", "foto": "BillieJoeArmstrong.jpg", "personaje": "Himself"}, {"nombre": "Rodney Bingenheimer", "foto": "RodneyBingenheimer.jpg", "personaje": "Himself"}, {"nombre": "Rodney Bingenheimer", "foto": "RodneyBingenheimer.jpg", "personaje": "Himself"}, {"nombre": "Rodney Bingenheimer", "foto": "RodneyBingenheimer.jpg", "personaje": "Himself"}, {"nombre": "Rodney Bingenheimer", "foto": "RodneyBingenheimer.jpg", "personaje": "Himself"}, {"nombre": "Rodney Bingenheimer", "foto": "RodneyBingenheimer.jpg", "personaje": "Himself"}, {"nombre": "Rodney Bingenheimer", "foto": "RodneyBingenheimer.jpg", "personaje": "Himself"}], "titulo": "Bad Reputation", "fechaCompra": "2018-10-7", "id": 1, "valoracion": 2.7}, {"director": "Karey Kirkpatrick, Jason Reisig", "sinopsis": "A Yeti is convinced that the elusive creatures known as hoomans really do exist", "genero": "Aventura", "cantidad": 8, "poster": "Smallfoot.jpg", "precio": 18, "anno": 2018, "actores": [{"nombre": "Jake Lloyd", "foto": "anakin.jpg", "personaje": "Anakin Skywalker"}, {"nombre": "Ewan McGregor", "foto": "kenobi.jpg", "personaje": "Obi-Wan Kenobi"}], "titulo": "Smallfoot", "fechaCompra": "2018-10-27", "id": 3, "valoracion": 5}, {"anno": 199, "sinopsis": "Vente al lado oscuro Obi-Wan", "genero": "Terror", "cantidad": 7, "poster": "The_nun.jpg", "precio": 18, "director": "Corin Hardy", "actores": [{"nombre": "Jake Lloyd", "foto": "anakin.jpg", "personaje": "Anakin Skywalker"}, {"nombre": "Ewan McGregor", "foto": "kenobi.jpg", "personaje": "Obi-Wan Kenobi"}], "titulo": "La monja", "fechaCompra": "2018-10-27", "id": 2, "valoracion": 5}, {"anno": 2018, "sinopsis": "Documentary about ut rock star Joan Jett.", "genero": "Documental", "cantidad": 4, "poster": "Bad_reputation.jpg", "precio": 18.99, "director": "Kevin Kerslake", "actores": [{"nombre": "Billie Joe Armstrong", "foto": "BillieJoeArmstrong.jpg", "personaje": "Himself"}, {"nombre": "Rodney Bingenheimer", "foto": "RodneyBingenheimer.jpg", "personaje": "Himself"}, {"nombre": "Rodney Bingenheimer", "foto": "RodneyBingenheimer.jpg", "personaje": "Himself"}, {"nombre": "Rodney Bingenheimer", "foto": "RodneyBingenheimer.jpg", "personaje": "Himself"}, {"nombre": "Rodney Bingenheimer", "foto": "RodneyBingenheimer.jpg", "personaje": "Himself"}, {"nombre": "Rodney Bingenheimer", "foto": "RodneyBingenheimer.jpg", "personaje": "Himself"}, {"nombre": "Rodney Bingenheimer", "foto": "RodneyBingenheimer.jpg", "personaje": "Himself"}], "titulo": "Bad Reputation", "fechaCompra": "2018-10-27", "id": 1, "valoracion": 2.7}, {"anno": 2018, "sinopsis": "Set in riot-torn, near-future Los Angeles", "genero": "Aventura", "cantidad": 1, "poster": "Hotel_Artemis.jpg", "precio": 19, "director": "Drew Pearce", "actores": [{"nombre": "Jake Lloyd", "foto": "anakin.jpg", "personaje": "Anakin Skywalker"}, {"nombre": "Ewan McGregor", "foto": "kenobi.jpg", "personaje": "Obi-Wan Kenobi"}], "titulo": "Hotel Artemissssssssssssssaa hotel de hotel de hotel", "fechaCompra": "2018-10-27", "id": 4, "valoracion": 5}]}